DjangoGirlsTaipeiTutorial/README.md
DjangoGirlsTaipeiTutorial/__init__.py
DjangoGirlsTaipeiTutorial/__main__.py
DjangoGirlsTaipeiTutorial/file.epub
DjangoGirlsTaipeiTutorial/index.html
DjangoGirlsTaipeiTutorial/css/__init__.py
DjangoGirlsTaipeiTutorial/css/annotations.css
DjangoGirlsTaipeiTutorial/css/main.css
DjangoGirlsTaipeiTutorial/css/normalize.css
DjangoGirlsTaipeiTutorial/css/popup.css
DjangoGirlsTaipeiTutorial/font/__init__.py
DjangoGirlsTaipeiTutorial/font/fontello.eot
DjangoGirlsTaipeiTutorial/font/fontello.svg
DjangoGirlsTaipeiTutorial/font/fontello.ttf
DjangoGirlsTaipeiTutorial/font/fontello.woff
DjangoGirlsTaipeiTutorial/img/__init__.py
DjangoGirlsTaipeiTutorial/img/annotator-glyph-sprite.png
DjangoGirlsTaipeiTutorial/img/annotator-icon-sprite.png
DjangoGirlsTaipeiTutorial/img/apple-touch-icon.png
DjangoGirlsTaipeiTutorial/img/cancelfullscreen.png
DjangoGirlsTaipeiTutorial/img/close.png
DjangoGirlsTaipeiTutorial/img/fullscreen.png
DjangoGirlsTaipeiTutorial/img/loader.gif
DjangoGirlsTaipeiTutorial/img/menu-icon.png
DjangoGirlsTaipeiTutorial/img/save.png
DjangoGirlsTaipeiTutorial/img/saved.png
DjangoGirlsTaipeiTutorial/img/settings-s.png
DjangoGirlsTaipeiTutorial/img/settings.png
DjangoGirlsTaipeiTutorial/img/star.png
DjangoGirlsTaipeiTutorial/js/__init__.py
DjangoGirlsTaipeiTutorial/js/epub.js
DjangoGirlsTaipeiTutorial/js/epub.min.js
DjangoGirlsTaipeiTutorial/js/epub.min.map
DjangoGirlsTaipeiTutorial/js/hooks.min.js
DjangoGirlsTaipeiTutorial/js/hooks.min.map
DjangoGirlsTaipeiTutorial/js/reader.js
DjangoGirlsTaipeiTutorial/js/reader.js.map
DjangoGirlsTaipeiTutorial/js/reader.min.js
DjangoGirlsTaipeiTutorial/js/reader.min.map
DjangoGirlsTaipeiTutorial/js/hooks/__init__.py
DjangoGirlsTaipeiTutorial/js/hooks/extensions/__init__.py
DjangoGirlsTaipeiTutorial/js/hooks/extensions/highlight.js
DjangoGirlsTaipeiTutorial/js/libs/__init__.py
DjangoGirlsTaipeiTutorial/js/libs/jquery.min.js
DjangoGirlsTaipeiTutorial/js/libs/localforage.min.js
django_girls_taipei_tutorial-2024.3.1.0.dist-info/METADATA
django_girls_taipei_tutorial-2024.3.1.0.dist-info/WHEEL
django_girls_taipei_tutorial-2024.3.1.0.dist-info/entry_points.txt
django_girls_taipei_tutorial-2024.3.1.0.dist-info/top_level.txt
django_girls_taipei_tutorial-2024.3.1.0.dist-info/RECORD
